setup.py
kael/__init__.py
kael/cli.py
kael/cron.py
kael/daemon.py
kael/microservice.py
kael/producer.py
kael/service_manage.py
kael/validate.py
kael/web_cli.py
kael/work_frame.py
kael.egg-info/PKG-INFO
kael.egg-info/SOURCES.txt
kael.egg-info/dependency_links.txt
kael.egg-info/entry_points.txt
kael.egg-info/not-zip-safe
kael.egg-info/requires.txt
kael.egg-info/top_level.txt
kael/web_admin/__init__.py
kael/web_admin/blueprint_factory.py
kael/web_admin/common.py
kael/web_admin/exceptions.py
kael/web_admin/forms.py
kael/web_admin/monkey.py
kael/web_admin/settings.py
kael/web_admin/admin/__init__.py
kael/web_admin/admin/view.py
kael/web_admin/api/__init__.py
kael/web_admin/api/view.py