Metadata-Version: 1.1
Name: kael
Version: 0.0.5
Summary: A micro service framework based on MQ
Home-page: https://github.com/360skyeye
Author: 360skyeye
Author-email: liqiongxiang@b.360.cn
License: Apache-2.0
Platform: any
Classifier: Development Status :: 4 - Beta
Classifier: Environment :: Web Environment
Classifier: Intended Audience :: Developers
Classifier: Operating System :: OS Independent
Classifier: Programming Language :: Python
Classifier: Programming Language :: Python :: 2
Classifier: Programming Language :: Python :: 2.7
Classifier: Topic :: Internet :: WWW/HTTP :: Dynamic Content
Classifier: Topic :: Software Development :: Libraries :: Python Modules
